candy_DynamicNetworks-0.0.15.data/purelib/LICENSE
candy_DynamicNetworks-0.0.15.data/purelib/README.md
candy_DynamicNetworks-0.0.15.data/purelib/__init__.py
candy_DynamicNetworks-0.0.15.data/purelib/candy.cpython-310-x86_64-linux-gnu.so
candy_DynamicNetworks-0.0.15.data/purelib/pyproject.toml
candy_DynamicNetworks-0.0.15.data/purelib/candy_DynamicNetworks.egg-info/PKG-INFO
candy_DynamicNetworks-0.0.15.data/purelib/candy_DynamicNetworks.egg-info/SOURCES.txt
candy_DynamicNetworks-0.0.15.data/purelib/candy_DynamicNetworks.egg-info/dependency_links.txt
candy_DynamicNetworks-0.0.15.data/purelib/candy_DynamicNetworks.egg-info/top_level.txt
candy_DynamicNetworks-0.0.15.dist-info/LICENSE
candy_DynamicNetworks-0.0.15.dist-info/METADATA
candy_DynamicNetworks-0.0.15.dist-info/WHEEL
candy_DynamicNetworks-0.0.15.dist-info/top_level.txt
candy_DynamicNetworks-0.0.15.dist-info/RECORD
