Metadata-Version: 2.1
Name: candy-DynamicNetworks
Version: 0.0.15
Summary: CANDY software for updating dynamic networks
Home-page: https://sites.google.com/view/candy-nsf/CANDY
Author: Sriram Srinivasan
Author-email: candy.nsf@gmail.com
License: UNKNOWN
Platform: UNKNOWN
License-File: LICENSE
